ghostos_container-0.2.7.dist-info/METADATA
ghostos_container-0.2.7.dist-info/WHEEL
ghostos_container-0.2.7.dist-info/entry_points.txt
ghostos_container-0.2.7.dist-info/licenses/LICENSE
ghostos_container.py
ghostos_container-0.2.7.dist-info/RECORD
