Metadata-Version: 2.1
Name: ghostos-container
Version: 0.2.7
Summary: the ioc container useful for Interface oriented programming
Author-Email: thirdgerb <thirdgerb@gmail.com>
License: MIT
Project-URL: Homepage, https://github.com/ghost-in-moss/GhostOS
Project-URL: Repository, https://github.com/ghost-in-moss/GhostOS
Requires-Python: >=3.10
